LICENSE-APACHE
LICENSE-MIT
MANIFEST.in
README.rst
setup.py
portainer_py/__init__.py
portainer_py/cli.py
portainer_py/portainer.py
portainer_py.egg-info/PKG-INFO
portainer_py.egg-info/SOURCES.txt
portainer_py.egg-info/dependency_links.txt
portainer_py.egg-info/entry_points.txt
portainer_py.egg-info/requires.txt
portainer_py.egg-info/top_level.txt
portainer_py/api_versions/__init__.py
portainer_py/api_versions/exceptions.py
portainer_py/api_versions/portainer_1_17.py
portainer_py/api_versions/portainer_1_18.py
portainer_py/api_versions/portainer_base.py
tests/__init__.py
tests/test_cli.py
tests/test_version_finder.py