Metadata-Version: 2.1
Name: portainer-py
Version: 0.7.2
Summary: Package to help deploy projects to portainer
Home-page: https://github.com/bob-codingdutchmen/portainer-py
Author: Bob Vork
Author-email: bob@theothersonline.eu
Maintainer: Bob Vork
Maintainer-email: bob@theothersonline.eu
License: MIT
Platform: UNKNOWN
Classifier: Development Status :: 4 - Beta
Classifier: Intended Audience :: Developers
Classifier: License :: OSI Approved :: MIT License
Classifier: Natural Language :: English
Classifier: Operating System :: OS Independent
Classifier: Programming Language :: Python :: 3.5
Classifier: Programming Language :: Python :: 3.6
Classifier: Programming Language :: Python :: Implementation :: CPython
Classifier: Programming Language :: Python :: Implementation :: PyPy
